hikari_orchestrator/__init__.py
hikari_orchestrator/__main__.py
hikari_orchestrator/_bot.py
hikari_orchestrator/_client.py
hikari_orchestrator/_service.py
hikari_orchestrator/_ssl.py
hikari_orchestrator/py.typed
hikari_orchestrator/_protos/__init__.py
hikari_orchestrator/_protos/schema_pb2.py
hikari_orchestrator/_protos/schema_pb2.pyi
hikari_orchestrator/_protos/schema_pb2_grpc.py
hikari_orchestrator/_protos/schema_pb2_grpc.pyi
hikari_orchestrator-0.2.1.dist-info/entry_points.txt
hikari_orchestrator-0.2.1.dist-info/LICENSE
hikari_orchestrator-0.2.1.dist-info/WHEEL
hikari_orchestrator-0.2.1.dist-info/METADATA
hikari_orchestrator-0.2.1.dist-info/RECORD
